truckpad/bottle/cors.py
bottle_cors-0.1.5.dist-info/LICENSE
bottle_cors-0.1.5.dist-info/METADATA
bottle_cors-0.1.5.dist-info/WHEEL
bottle_cors-0.1.5.dist-info/top_level.txt
bottle_cors-0.1.5.dist-info/RECORD
