Metadata-Version: 2.1
Name: bottle-cors
Version: 0.1.5
Summary: CORS plugin for Bottle framework
Home-page: https://github.com/truckpad/bottle-cors
Author: Marcos Araujo Sobrinho
Author-email: marcos.sobrinho@truckpad.com.br
License: UNKNOWN
Platform: UNKNOWN
Classifier: Development Status :: 2 - Pre-Alpha
Classifier: Operating System :: POSIX
Classifier: Programming Language :: Python :: 3
Classifier: Topic :: Internet :: WWW/HTTP
